main.py
github_user_activity_89aman-0.1.0.dist-info/METADATA
github_user_activity_89aman-0.1.0.dist-info/WHEEL
github_user_activity_89aman-0.1.0.dist-info/entry_points.txt
github_user_activity_89aman-0.1.0.dist-info/top_level.txt
github_user_activity_89aman-0.1.0.dist-info/RECORD
